{"surah":53,"name_ar":"النجم","name_en":"An-Najm","ayah_count":62,"riwayat":["hafs","warsh"],"bismillah":{"hafs":"بِسْمِ ٱللَّهِ ٱلرَّحْمَٰنِ ٱلرَّحِيمِ","warsh":"بِسۡمِ اِ۬للَّهِ اِ۬لرَّحۡمَٰنِ اِ۬لرَّحِيمِ"},"ayat":[{"n":1,"key":"53:1","text":{"hafs":"وَٱلنَّجْمِ إِذَا هَوَىٰ","warsh":"وَالنَّجْمِ إِذَا هَو۪ىٰ"},"words":{"hafs":["وَٱلنَّجْمِ","إِذَا","هَوَىٰ"],"warsh":["وَالنَّجْمِ","إِذَا","هَو۪ىٰ"]},"sajda":false},{"n":2,"key":"53:2","text":{"hafs":"مَا ضَلَّ صَاحِبُكُمْ وَمَا غَوَىٰ","warsh":"مَا ضَلَّ صَٰحِبُكُمْ وَمَا غَو۪ىٰ"},"words":{"hafs":["مَا","ضَلَّ","صَاحِبُكُمْ","وَمَا","غَوَىٰ"],"warsh":["مَا","ضَلَّ","صَٰحِبُكُمْ","وَمَا","غَو۪ىٰ"]},"sajda":false},{"n":3,"key":"53:3","text":{"hafs":"وَمَا يَنطِقُ عَنِ ٱلْهَوَىٰٓ","warsh":"وَمَا يَنطِقُ عَنِ اِ۬لْهَو۪ىٰٓ"},"words":{"hafs":["وَمَا","يَنطِقُ","عَنِ","ٱلْهَوَىٰٓ"],"warsh":["وَمَا","يَنطِقُ","عَنِ","اِ۬لْهَو۪ىٰٓ"]},"sajda":false},{"n":4,"key":"53:4","text":{"hafs":"إِنْ هُوَ إِلَّا وَحْىٌ يُوحَىٰ","warsh":"إِنْ هُوَ إِلَّا وَحْيٞ يُوح۪ىٰۖ"},"words":{"hafs":["إِنْ","هُوَ","إِلَّا","وَحْىٌ","يُوحَىٰ"],"warsh":["إِنْ","هُوَ","إِلَّا","وَحْيٞ","يُوح۪ىٰۖ"]},"sajda":false},{"n":5,"key":"53:5","text":{"hafs":"عَلَّمَهُۥ شَدِيدُ ٱلْقُوَىٰ","warsh":"عَلَّمَهُۥ شَدِيدُ اُ۬لْقُو۪ىٰ"},"words":{"hafs":["عَلَّمَهُۥ","شَدِيدُ","ٱلْقُوَىٰ"],"warsh":["عَلَّمَهُۥ","شَدِيدُ","اُ۬لْقُو۪ىٰ"]},"sajda":false},{"n":6,"key":"53:6","text":{"hafs":"ذُو مِرَّةٍ فَٱسْتَوَىٰ","warsh":"ذُو مِرَّةٖۖ فَاسْتَو۪ىٰ"},"words":{"hafs":["ذُو","مِرَّةٍ","فَٱسْتَوَىٰ"],"warsh":["ذُو","مِرَّةٖۖ","فَاسْتَو۪ىٰ"]},"sajda":false},{"n":7,"key":"53:7","text":{"hafs":"وَهُوَ بِٱلْأُفُقِ ٱلْأَعْلَىٰ","warsh":"وَهُوَ بِالُافُقِ اِ۬لَاعْل۪ىٰۖ"},"words":{"hafs":["وَهُوَ","بِٱلْأُفُقِ","ٱلْأَعْلَىٰ"],"warsh":["وَهُوَ","بِالُافُقِ","اِ۬لَاعْل۪ىٰۖ"]},"sajda":false},{"n":8,"key":"53:8","text":{"hafs":"ثُمَّ دَنَا فَتَدَلَّىٰ","warsh":"ثُمَّ دَنَا فَتَدَلّ۪ىٰ"},"words":{"hafs":["ثُمَّ","دَنَا","فَتَدَلَّىٰ"],"warsh":["ثُمَّ","دَنَا","فَتَدَلّ۪ىٰ"]},"sajda":false},{"n":9,"key":"53:9","text":{"hafs":"فَكَانَ قَابَ قَوْسَيْنِ أَوْ أَدْنَىٰ","warsh":"فَكَانَ قَابَ قَوْسَيْنِ أَوَ اَدْن۪ىٰۖ"},"words":{"hafs":["فَكَانَ","قَابَ","قَوْسَيْنِ","أَوْ","أَدْنَىٰ"],"warsh":["فَكَانَ","قَابَ","قَوْسَيْنِ","أَوَ","اَدْن۪ىٰۖ"]},"sajda":false},{"n":10,"key":"53:10","text":{"hafs":"فَأَوْحَىٰٓ إِلَىٰ عَبْدِهِۦ مَآ أَوْحَىٰ","warsh":"فَأَوْح۪ىٰٓ إِلَىٰ عَبْدِهِۦ مَآ أَوْح۪ىٰۖ"},"words":{"hafs":["فَأَوْحَىٰٓ","إِلَىٰ","عَبْدِهِۦ","مَآ","أَوْحَىٰ"],"warsh":["فَأَوْح۪ىٰٓ","إِلَىٰ","عَبْدِهِۦ","مَآ","أَوْح۪ىٰۖ"]},"sajda":false},{"n":11,"key":"53:11","text":{"hafs":"مَا كَذَبَ ٱلْفُؤَادُ مَا رَأَىٰٓ","warsh":"مَا كَذَبَ اَ۬لْفُؤَادُ مَا ر۪أ۪ىٰٓۖ"},"words":{"hafs":["مَا","كَذَبَ","ٱلْفُؤَادُ","مَا","رَأَىٰٓ"],"warsh":["مَا","كَذَبَ","اَ۬لْفُؤَادُ","مَا","ر۪أ۪ىٰٓۖ"]},"sajda":false},{"n":12,"key":"53:12","text":{"hafs":"أَفَتُمَٰرُونَهُۥ عَلَىٰ مَا يَرَىٰ","warsh":"أَفَتُمَٰرُونَهُۥ عَلَىٰ مَا يَر۪ىٰۖ"},"words":{"hafs":["أَفَتُمَٰرُونَهُۥ","عَلَىٰ","مَا","يَرَىٰ"],"warsh":["أَفَتُمَٰرُونَهُۥ","عَلَىٰ","مَا","يَر۪ىٰۖ"]},"sajda":false},{"n":13,"key":"53:13","text":{"hafs":"وَلَقَدْ رَءَاهُ نَزْلَةً أُخْرَىٰ","warsh":"وَلَقَدْ ر۪ء۪اهُ نَزْلَةً ا۟خْر۪ىٰ"},"words":{"hafs":["وَلَقَدْ","رَءَاهُ","نَزْلَةً","أُخْرَىٰ"],"warsh":["وَلَقَدْ","ر۪ء۪اهُ","نَزْلَةً","ا۟خْر۪ىٰ"]},"sajda":false},{"n":14,"key":"53:14","text":{"hafs":"عِندَ سِدْرَةِ ٱلْمُنتَهَىٰ","warsh":"عِندَ سِدْرَةِ اِ۬لْمُنتَه۪ىٰ"},"words":{"hafs":["عِندَ","سِدْرَةِ","ٱلْمُنتَهَىٰ"],"warsh":["عِندَ","سِدْرَةِ","اِ۬لْمُنتَه۪ىٰ"]},"sajda":false},{"n":15,"key":"53:15","text":{"hafs":"عِندَهَا جَنَّةُ ٱلْمَأْوَىٰٓ","warsh":"عِندَهَا جَنَّةُ اُ۬لْمَأْو۪ىٰٓ"},"words":{"hafs":["عِندَهَا","جَنَّةُ","ٱلْمَأْوَىٰٓ"],"warsh":["عِندَهَا","جَنَّةُ","اُ۬لْمَأْو۪ىٰٓ"]},"sajda":false},{"n":16,"key":"53:16","text":{"hafs":"إِذْ يَغْشَى ٱلسِّدْرَةَ مَا يَغْشَىٰ","warsh":"إِذْ يَغْشَى اَ۬لسِّدْرَةَ مَا يَغْش۪ىٰۖ"},"words":{"hafs":["إِذْ","يَغْشَى","ٱلسِّدْرَةَ","مَا","يَغْشَىٰ"],"warsh":["إِذْ","يَغْشَى","اَ۬لسِّدْرَةَ","مَا","يَغْش۪ىٰۖ"]},"sajda":false},{"n":17,"key":"53:17","text":{"hafs":"مَا زَاغَ ٱلْبَصَرُ وَمَا طَغَىٰ","warsh":"مَا زَاغَ اَ۬لْبَصَرُ وَمَا طَغ۪ىٰۖ"},"words":{"hafs":["مَا","زَاغَ","ٱلْبَصَرُ","وَمَا","طَغَىٰ"],"warsh":["مَا","زَاغَ","اَ۬لْبَصَرُ","وَمَا","طَغ۪ىٰۖ"]},"sajda":false},{"n":18,"key":"53:18","text":{"hafs":"لَقَدْ رَأَىٰ مِنْ ءَايَٰتِ رَبِّهِ ٱلْكُبْرَىٰٓ","warsh":"لَقَدْ ر۪أ۪ىٰ مِنَ اٰيَٰتِ رَبِّهِ اِ۬لْكُبْر۪ىٰٓۖ"},"words":{"hafs":["لَقَدْ","رَأَىٰ","مِنْ","ءَايَٰتِ","رَبِّهِ","ٱلْكُبْرَىٰٓ"],"warsh":["لَقَدْ","ر۪أ۪ىٰ","مِنَ","اٰيَٰتِ","رَبِّهِ","اِ۬لْكُبْر۪ىٰٓۖ"]},"sajda":false},{"n":19,"key":"53:19","text":{"hafs":"أَفَرَءَيْتُمُ ٱللَّٰتَ وَٱلْعُزَّىٰ","warsh":"أَفَرَٰٓيْتُمُ اُ۬للَّٰتَ وَالْعُزّ۪ىٰ"},"words":{"hafs":["أَفَرَءَيْتُمُ","ٱللَّٰتَ","وَٱلْعُزَّىٰ"],"warsh":["أَفَرَٰٓيْتُمُ","اُ۬للَّٰتَ","وَالْعُزّ۪ىٰ"]},"sajda":false},{"n":20,"key":"53:20","text":{"hafs":"وَمَنَوٰةَ ٱلثَّالِثَةَ ٱلْأُخْرَىٰٓ","warsh":"وَمَنَوٰةَ اَ۬لثَّالِثَةَ اَ۬لُاخْر۪ىٰٓ"},"words":{"hafs":["وَمَنَوٰةَ","ٱلثَّالِثَةَ","ٱلْأُخْرَىٰٓ"],"warsh":["وَمَنَوٰةَ","اَ۬لثَّالِثَةَ","اَ۬لُاخْر۪ىٰٓ"]},"sajda":false},{"n":21,"key":"53:21","text":{"hafs":"أَلَكُمُ ٱلذَّكَرُ وَلَهُ ٱلْأُنثَىٰ","warsh":"أَلَكُمُ اُ۬لذَّكَرُ وَلَهُ اُ۬لُانث۪ىٰۖ"},"words":{"hafs":["أَلَكُمُ","ٱلذَّكَرُ","وَلَهُ","ٱلْأُنثَىٰ"],"warsh":["أَلَكُمُ","اُ۬لذَّكَرُ","وَلَهُ","اُ۬لُانث۪ىٰۖ"]},"sajda":false},{"n":22,"key":"53:22","text":{"hafs":"تِلْكَ إِذًا قِسْمَةٌ ضِيزَىٰٓ","warsh":"تِلْكَ إِذاٗ قِسْمَةٞ ضِيز۪ىٰٓۖ"},"words":{"hafs":["تِلْكَ","إِذًا","قِسْمَةٌ","ضِيزَىٰٓ"],"warsh":["تِلْكَ","إِذاٗ","قِسْمَةٞ","ضِيز۪ىٰٓۖ"]},"sajda":false},{"n":23,"key":"53:23","text":{"hafs":"إِنْ هِىَ إِلَّآ أَسْمَآءٌ سَمَّيْتُمُوهَآ أَنتُمْ وَءَابَآؤُكُم مَّآ أَنزَلَ ٱللَّهُ بِهَا مِن سُلْطَٰنٍ ۚ إِن يَتَّبِعُونَ إِلَّا ٱلظَّنَّ وَمَا تَهْوَى ٱلْأَنفُسُ ۖ وَلَقَدْ جَآءَهُم مِّن رَّبِّهِمُ ٱلْهُدَىٰٓ","warsh":"إِنْ هِيَ إِلَّآ أَسْمَآءٞ سَمَّيْتُمُوهَآ أَنتُمْ وَءَابَآؤُكُم مَّآ أَنزَلَ اَ۬للَّهُ بِهَا مِن سُلْطَٰنٍۖ اِنْ يَّتَّبِعُونَ إِلَّا اَ۬لظَّنَّ وَمَا تَهْوَى اَ۬لَانفُسُۖ وَلَقَدْ جَآءَهُم مِّن رَّبِّهِمُ اُ۬لْهُد۪ىٰٓۖ"},"words":{"hafs":["إِنْ","هِىَ","إِلَّآ","أَسْمَآءٌ","سَمَّيْتُمُوهَآ","أَنتُمْ","وَءَابَآؤُكُم","مَّآ","أَنزَلَ","ٱللَّهُ","بِهَا","مِن","سُلْطَٰنٍ","إِن","يَتَّبِعُونَ","إِلَّا","ٱلظَّنَّ","وَمَا","تَهْوَى","ٱلْأَنفُسُ","وَلَقَدْ","جَآءَهُم","مِّن","رَّبِّهِمُ","ٱلْهُدَىٰٓ"],"warsh":["إِنْ","هِيَ","إِلَّآ","أَسْمَآءٞ","سَمَّيْتُمُوهَآ","أَنتُمْ","وَءَابَآؤُكُم","مَّآ","أَنزَلَ","اَ۬للَّهُ","بِهَا","مِن","سُلْطَٰنٍۖ","اِنْ","يَّتَّبِعُونَ","إِلَّا","اَ۬لظَّنَّ","وَمَا","تَهْوَى","اَ۬لَانفُسُۖ","وَلَقَدْ","جَآءَهُم","مِّن","رَّبِّهِمُ","اُ۬لْهُد۪ىٰٓۖ"]},"sajda":false},{"n":24,"key":"53:24","text":{"hafs":"أَمْ لِلْإِنسَٰنِ مَا تَمَنَّىٰ","warsh":"أَمْ لِلِانسَٰنِ مَا تَمَنّ۪ىٰۖ"},"words":{"hafs":["أَمْ","لِلْإِنسَٰنِ","مَا","تَمَنَّىٰ"],"warsh":["أَمْ","لِلِانسَٰنِ","مَا","تَمَنّ۪ىٰۖ"]},"sajda":false},{"n":25,"key":"53:25","text":{"hafs":"فَلِلَّهِ ٱلْـَٔاخِرَةُ وَٱلْأُولَىٰ","warsh":"فَلِلهِ اِ۬لَاخِرَةُ وَالُاول۪ىٰۖ"},"words":{"hafs":["فَلِلَّهِ","ٱلْـَٔاخِرَةُ","وَٱلْأُولَىٰ"],"warsh":["فَلِلهِ","اِ۬لَاخِرَةُ","وَالُاول۪ىٰۖ"]},"sajda":false},{"n":26,"key":"53:26","text":{"hafs":"وَكَم مِّن مَّلَكٍ فِى ٱلسَّمَٰوَٰتِ لَا تُغْنِى شَفَٰعَتُهُمْ شَيْـًٔا إِلَّا مِنۢ بَعْدِ أَن يَأْذَنَ ٱللَّهُ لِمَن يَشَآءُ وَيَرْضَىٰٓ","warsh":"وَكَم مِّن مَّلَكٖ فِے اِ۬لسَّمَٰوَٰتِ لَا تُغْنِے شَفَٰعَتُهُمْ شَئْاً اِلَّا مِنۢ بَعْدِ أَنْ يَّاذَنَ اَ۬للَّهُ لِمَنْ يَّشَآءُ وَيَرْض۪ىٰٓۖ"},"words":{"hafs":["وَكَم","مِّن","مَّلَكٍ","فِى","ٱلسَّمَٰوَٰتِ","لَا","تُغْنِى","شَفَٰعَتُهُمْ","شَيْـًٔا","إِلَّا","مِنۢ","بَعْدِ","أَن","يَأْذَنَ","ٱللَّهُ","لِمَن","يَشَآءُ","وَيَرْضَىٰٓ"],"warsh":["وَكَم","مِّن","مَّلَكٖ","فِے","اِ۬لسَّمَٰوَٰتِ","لَا","تُغْنِے","شَفَٰعَتُهُمْ","شَئْاً","اِلَّا","مِنۢ","بَعْدِ","أَنْ","يَّاذَنَ","اَ۬للَّهُ","لِمَنْ","يَّشَآءُ","وَيَرْض۪ىٰٓۖ"]},"sajda":false},{"n":27,"key":"53:27","text":{"hafs":"إِنَّ ٱلَّذِينَ لَا يُؤْمِنُونَ بِٱلْـَٔاخِرَةِ لَيُسَمُّونَ ٱلْمَلَٰٓئِكَةَ تَسْمِيَةَ ٱلْأُنثَىٰ","warsh":"إِنَّ اَ۬لذِينَ لَا يُومِنُونَ بِالَاخِرَةِ لَيُسَمُّونَ اَ۬لْمَلَٰٓئِكَةَ تَسْمِيَةَ اَ۬لُانث۪ىٰۖ"},"words":{"hafs":["إِنَّ","ٱلَّذِينَ","لَا","يُؤْمِنُونَ","بِٱلْـَٔاخِرَةِ","لَيُسَمُّونَ","ٱلْمَلَٰٓئِكَةَ","تَسْمِيَةَ","ٱلْأُنثَىٰ"],"warsh":["إِنَّ","اَ۬لذِينَ","لَا","يُومِنُونَ","بِالَاخِرَةِ","لَيُسَمُّونَ","اَ۬لْمَلَٰٓئِكَةَ","تَسْمِيَةَ","اَ۬لُانث۪ىٰۖ"]},"sajda":false},{"n":28,"key":"53:28","text":{"hafs":"وَمَا لَهُم بِهِۦ مِنْ عِلْمٍ ۖ إِن يَتَّبِعُونَ إِلَّا ٱلظَّنَّ ۖ وَإِنَّ ٱلظَّنَّ لَا يُغْنِى مِنَ ٱلْحَقِّ شَيْـًٔا","warsh":"وَمَا لَهُم بِهِۦ مِنْ عِلْمٍۖ اِنْ يَّتَّبِعُونَ إِلَّا اَ۬لظَّنَّۖ وَإِنَّ اَ۬لظَّنَّ لَا يُغْنِے مِنَ اَ۬لْحَقِّ شَئْاٗۖ"},"words":{"hafs":["وَمَا","لَهُم","بِهِۦ","مِنْ","عِلْمٍ","إِن","يَتَّبِعُونَ","إِلَّا","ٱلظَّنَّ","وَإِنَّ","ٱلظَّنَّ","لَا","يُغْنِى","مِنَ","ٱلْحَقِّ","شَيْـًٔا"],"warsh":["وَمَا","لَهُم","بِهِۦ","مِنْ","عِلْمٍۖ","اِنْ","يَّتَّبِعُونَ","إِلَّا","اَ۬لظَّنَّۖ","وَإِنَّ","اَ۬لظَّنَّ","لَا","يُغْنِے","مِنَ","اَ۬لْحَقِّ","شَئْاٗۖ"]},"sajda":false},{"n":29,"key":"53:29","text":{"hafs":"فَأَعْرِضْ عَن مَّن تَوَلَّىٰ عَن ذِكْرِنَا وَلَمْ يُرِدْ إِلَّا ٱلْحَيَوٰةَ ٱلدُّنْيَا","warsh":"فَأَعْرِضْ عَن مَّن تَوَلّ۪ىٰ عَن ذِكْرِنَا وَلَمْ يُرِدِ اِلَّا اَ۬لْحَيَوٰةَ اَ۬لدُّنْي۪اۖ"},"words":{"hafs":["فَأَعْرِضْ","عَن","مَّن","تَوَلَّىٰ","عَن","ذِكْرِنَا","وَلَمْ","يُرِدْ","إِلَّا","ٱلْحَيَوٰةَ","ٱلدُّنْيَا"],"warsh":["فَأَعْرِضْ","عَن","مَّن","تَوَلّ۪ىٰ","عَن","ذِكْرِنَا","وَلَمْ","يُرِدِ","اِلَّا","اَ۬لْحَيَوٰةَ","اَ۬لدُّنْي۪اۖ"]},"sajda":false},{"n":30,"key":"53:30","text":{"hafs":"ذَٰلِكَ مَبْلَغُهُم مِّنَ ٱلْعِلْمِ ۚ إِنَّ رَبَّكَ هُوَ أَعْلَمُ بِمَن ضَلَّ عَن سَبِيلِهِۦ وَهُوَ أَعْلَمُ بِمَنِ ٱهْتَدَىٰ","warsh":"ذَٰلِكَ مَبْلَغُهُم مِّنَ اَ۬لْعِلْمِۖ إِنَّ رَبَّكَ هُوَ أَعْلَمُ بِمَن ضَلَّ عَن سَبِيلِهِۦۖ وَهُوَ أَعْلَمُ بِمَنِ اِ۪هْتَد۪ىٰۖ"},"words":{"hafs":["ذَٰلِكَ","مَبْلَغُهُم","مِّنَ","ٱلْعِلْمِ","إِنَّ","رَبَّكَ","هُوَ","أَعْلَمُ","بِمَن","ضَلَّ","عَن","سَبِيلِهِۦ","وَهُوَ","أَعْلَمُ","بِمَنِ","ٱهْتَدَىٰ"],"warsh":["ذَٰلِكَ","مَبْلَغُهُم","مِّنَ","اَ۬لْعِلْمِۖ","إِنَّ","رَبَّكَ","هُوَ","أَعْلَمُ","بِمَن","ضَلَّ","عَن","سَبِيلِهِۦۖ","وَهُوَ","أَعْلَمُ","بِمَنِ","اِ۪هْتَد۪ىٰۖ"]},"sajda":false},{"n":31,"key":"53:31","text":{"hafs":"وَلِلَّهِ مَا فِى ٱلسَّمَٰوَٰتِ وَمَا فِى ٱلْأَرْضِ لِيَجْزِىَ ٱلَّذِينَ أَسَٰٓـُٔوا۟ بِمَا عَمِلُوا۟ وَيَجْزِىَ ٱلَّذِينَ أَحْسَنُوا۟ بِٱلْحُسْنَى","warsh":"وَلِلهِ مَا فِے اِ۬لسَّمَٰوَٰتِ وَمَا فِے اِ۬لَارْضِ لِيَجْزِيَ اَ۬لذِينَ أَسَٰٓـُٔواْ بِمَا عَمِلُواْ وَيَجْزِيَ اَ۬لذِينَ أَحْسَنُواْ بِالْحُسْنَىۖ"},"words":{"hafs":["وَلِلَّهِ","مَا","فِى","ٱلسَّمَٰوَٰتِ","وَمَا","فِى","ٱلْأَرْضِ","لِيَجْزِىَ","ٱلَّذِينَ","أَسَٰٓـُٔوا۟","بِمَا","عَمِلُوا۟","وَيَجْزِىَ","ٱلَّذِينَ","أَحْسَنُوا۟","بِٱلْحُسْنَى"],"warsh":["وَلِلهِ","مَا","فِے","اِ۬لسَّمَٰوَٰتِ","وَمَا","فِے","اِ۬لَارْضِ","لِيَجْزِيَ","اَ۬لذِينَ","أَسَٰٓـُٔواْ","بِمَا","عَمِلُواْ","وَيَجْزِيَ","اَ۬لذِينَ","أَحْسَنُواْ","بِالْحُسْنَىۖ"]},"sajda":false},{"n":32,"key":"53:32","text":{"hafs":"ٱلَّذِينَ يَجْتَنِبُونَ كَبَٰٓئِرَ ٱلْإِثْمِ وَٱلْفَوَٰحِشَ إِلَّا ٱللَّمَمَ ۚ إِنَّ رَبَّكَ وَٰسِعُ ٱلْمَغْفِرَةِ ۚ هُوَ أَعْلَمُ بِكُمْ إِذْ أَنشَأَكُم مِّنَ ٱلْأَرْضِ وَإِذْ أَنتُمْ أَجِنَّةٌ فِى بُطُونِ أُمَّهَٰتِكُمْ ۖ فَلَا تُزَكُّوٓا۟ أَنفُسَكُمْ ۖ هُوَ أَعْلَمُ بِمَنِ ٱتَّقَىٰٓ","warsh":"اَ۬لذِينَ يَجْتَنِبُونَ كَبَٰٓئِرَ اَ۬لِاثْمِ وَالْفَوَٰحِشَ إِلَّا اَ۬للَّمَمَۖ إِنَّ رَبَّكَ وَٰسِعُ اُ۬لْمَغْفِرَةِۖ هُوَ أَعْلَمُ بِكُمُۥٓ إِذَ اَنشَأَكُم مِّنَ اَ۬لَارْضِ وَإِذَ اَنتُمُۥٓ أَجِنَّةٞ فِے بُطُونِ أُمَّهَٰتِكُمْۖ فَلَا تُزَكُّوٓاْ أَنفُسَكُمْۖ هُوَ أَعْلَمُ بِمَنِ اِ۪تَّق۪ىٰٓۖ"},"words":{"hafs":["ٱلَّذِينَ","يَجْتَنِبُونَ","كَبَٰٓئِرَ","ٱلْإِثْمِ","وَٱلْفَوَٰحِشَ","إِلَّا","ٱللَّمَمَ","إِنَّ","رَبَّكَ","وَٰسِعُ","ٱلْمَغْفِرَةِ","هُوَ","أَعْلَمُ","بِكُمْ","إِذْ","أَنشَأَكُم","مِّنَ","ٱلْأَرْضِ","وَإِذْ","أَنتُمْ","أَجِنَّةٌ","فِى","بُطُونِ","أُمَّهَٰتِكُمْ","فَلَا","تُزَكُّوٓا۟","أَنفُسَكُمْ","هُوَ","أَعْلَمُ","بِمَنِ","ٱتَّقَىٰٓ"],"warsh":["اَ۬لذِينَ","يَجْتَنِبُونَ","كَبَٰٓئِرَ","اَ۬لِاثْمِ","وَالْفَوَٰحِشَ","إِلَّا","اَ۬للَّمَمَۖ","إِنَّ","رَبَّكَ","وَٰسِعُ","اُ۬لْمَغْفِرَةِۖ","هُوَ","أَعْلَمُ","بِكُمُۥٓ","إِذَ","اَنشَأَكُم","مِّنَ","اَ۬لَارْضِ","وَإِذَ","اَنتُمُۥٓ","أَجِنَّةٞ","فِے","بُطُونِ","أُمَّهَٰتِكُمْۖ","فَلَا","تُزَكُّوٓاْ","أَنفُسَكُمْۖ","هُوَ","أَعْلَمُ","بِمَنِ","اِ۪تَّق۪ىٰٓۖ"]},"sajda":false},{"n":33,"key":"53:33","text":{"hafs":"أَفَرَءَيْتَ ٱلَّذِى تَوَلَّىٰ","warsh":"أَفَرَٰٓيْتَ اَ۬لذِے تَوَلّ۪ىٰ"},"words":{"hafs":["أَفَرَءَيْتَ","ٱلَّذِى","تَوَلَّىٰ"],"warsh":["أَفَرَٰٓيْتَ","اَ۬لذِے","تَوَلّ۪ىٰ"]},"sajda":false},{"n":34,"key":"53:34","text":{"hafs":"وَأَعْطَىٰ قَلِيلًا وَأَكْدَىٰٓ","warsh":"وَأَعْط۪ىٰ قَلِيلاٗ وَأَكْد۪ىٰٓ"},"words":{"hafs":["وَأَعْطَىٰ","قَلِيلًا","وَأَكْدَىٰٓ"],"warsh":["وَأَعْط۪ىٰ","قَلِيلاٗ","وَأَكْد۪ىٰٓ"]},"sajda":false},{"n":35,"key":"53:35","text":{"hafs":"أَعِندَهُۥ عِلْمُ ٱلْغَيْبِ فَهُوَ يَرَىٰٓ","warsh":"أَعِندَهُۥ عِلْمُ اُ۬لْغَيْبِ فَهُوَ يَر۪ىٰٓۖ"},"words":{"hafs":["أَعِندَهُۥ","عِلْمُ","ٱلْغَيْبِ","فَهُوَ","يَرَىٰٓ"],"warsh":["أَعِندَهُۥ","عِلْمُ","اُ۬لْغَيْبِ","فَهُوَ","يَر۪ىٰٓۖ"]},"sajda":false},{"n":36,"key":"53:36","text":{"hafs":"أَمْ لَمْ يُنَبَّأْ بِمَا فِى صُحُفِ مُوسَىٰ","warsh":"أَمْ لَمْ يُنَبَّأْ بِمَا فِے صُحُفِ مُوس۪ىٰ"},"words":{"hafs":["أَمْ","لَمْ","يُنَبَّأْ","بِمَا","فِى","صُحُفِ","مُوسَىٰ"],"warsh":["أَمْ","لَمْ","يُنَبَّأْ","بِمَا","فِے","صُحُفِ","مُوس۪ىٰ"]},"sajda":false},{"n":37,"key":"53:37","text":{"hafs":"وَإِبْرَٰهِيمَ ٱلَّذِى وَفَّىٰٓ","warsh":"وَإِبْرَٰهِيمَ اَ۬لذِے وَفّ۪ىٰٓ"},"words":{"hafs":["وَإِبْرَٰهِيمَ","ٱلَّذِى","وَفَّىٰٓ"],"warsh":["وَإِبْرَٰهِيمَ","اَ۬لذِے","وَفّ۪ىٰٓ"]},"sajda":false},{"n":38,"key":"53:38","text":{"hafs":"أَلَّا تَزِرُ وَازِرَةٌ وِزْرَ أُخْرَىٰ","warsh":"أَلَّا تَزِرُ وَازِرَةٞ وِزْرَ أُخْر۪ىٰۖ"},"words":{"hafs":["أَلَّا","تَزِرُ","وَازِرَةٌ","وِزْرَ","أُخْرَىٰ"],"warsh":["أَلَّا","تَزِرُ","وَازِرَةٞ","وِزْرَ","أُخْر۪ىٰۖ"]},"sajda":false},{"n":39,"key":"53:39","text":{"hafs":"وَأَن لَّيْسَ لِلْإِنسَٰنِ إِلَّا مَا سَعَىٰ","warsh":"وَأَن لَّيْسَ لِلِانسَٰنِ إِلَّا مَا سَع۪ىٰۖ"},"words":{"hafs":["وَأَن","لَّيْسَ","لِلْإِنسَٰنِ","إِلَّا","مَا","سَعَىٰ"],"warsh":["وَأَن","لَّيْسَ","لِلِانسَٰنِ","إِلَّا","مَا","سَع۪ىٰۖ"]},"sajda":false},{"n":40,"key":"53:40","text":{"hafs":"وَأَنَّ سَعْيَهُۥ سَوْفَ يُرَىٰ","warsh":"وَأَنَّ سَعْيَهُۥ سَوْفَ يُر۪ىٰۖ"},"words":{"hafs":["وَأَنَّ","سَعْيَهُۥ","سَوْفَ","يُرَىٰ"],"warsh":["وَأَنَّ","سَعْيَهُۥ","سَوْفَ","يُر۪ىٰۖ"]},"sajda":false},{"n":41,"key":"53:41","text":{"hafs":"ثُمَّ يُجْزَىٰهُ ٱلْجَزَآءَ ٱلْأَوْفَىٰ","warsh":"ثُمَّ يُجْز۪يٰهُ اُ۬لْجَزَآءَ اَ۬لَاوْف۪ىٰۖ"},"words":{"hafs":["ثُمَّ","يُجْزَىٰهُ","ٱلْجَزَآءَ","ٱلْأَوْفَىٰ"],"warsh":["ثُمَّ","يُجْز۪يٰهُ","اُ۬لْجَزَآءَ","اَ۬لَاوْف۪ىٰۖ"]},"sajda":false},{"n":42,"key":"53:42","text":{"hafs":"وَأَنَّ إِلَىٰ رَبِّكَ ٱلْمُنتَهَىٰ","warsh":"وَأَنَّ إِلَىٰ رَبِّكَ اَ۬لْمُنتَه۪ىٰۖ"},"words":{"hafs":["وَأَنَّ","إِلَىٰ","رَبِّكَ","ٱلْمُنتَهَىٰ"],"warsh":["وَأَنَّ","إِلَىٰ","رَبِّكَ","اَ۬لْمُنتَه۪ىٰۖ"]},"sajda":false},{"n":43,"key":"53:43","text":{"hafs":"وَأَنَّهُۥ هُوَ أَضْحَكَ وَأَبْكَىٰ","warsh":"وَأَنَّهُۥ هُوَ أَضْحَكَ وَأَبْك۪ىٰۖ"},"words":{"hafs":["وَأَنَّهُۥ","هُوَ","أَضْحَكَ","وَأَبْكَىٰ"],"warsh":["وَأَنَّهُۥ","هُوَ","أَضْحَكَ","وَأَبْك۪ىٰۖ"]},"sajda":false},{"n":44,"key":"53:44","text":{"hafs":"وَأَنَّهُۥ هُوَ أَمَاتَ وَأَحْيَا","warsh":"وَأَنَّهُۥ هُوَ أَمَاتَ وَأَحْي۪اۖ"},"words":{"hafs":["وَأَنَّهُۥ","هُوَ","أَمَاتَ","وَأَحْيَا"],"warsh":["وَأَنَّهُۥ","هُوَ","أَمَاتَ","وَأَحْي۪اۖ"]},"sajda":false},{"n":45,"key":"53:45","text":{"hafs":"وَأَنَّهُۥ خَلَقَ ٱلزَّوْجَيْنِ ٱلذَّكَرَ وَٱلْأُنثَىٰ","warsh":"وَأَنَّهُۥ خَلَقَ اَ۬لزَّوْجَيْنِ اِ۬لذَّكَرَ وَالُانث۪ىٰ"},"words":{"hafs":["وَأَنَّهُۥ","خَلَقَ","ٱلزَّوْجَيْنِ","ٱلذَّكَرَ","وَٱلْأُنثَىٰ"],"warsh":["وَأَنَّهُۥ","خَلَقَ","اَ۬لزَّوْجَيْنِ","اِ۬لذَّكَرَ","وَالُانث۪ىٰ"]},"sajda":false},{"n":46,"key":"53:46","text":{"hafs":"مِن نُّطْفَةٍ إِذَا تُمْنَىٰ","warsh":"مِن نُّطْفَةٍ اِذَا تُمْن۪ىٰۖ"},"words":{"hafs":["مِن","نُّطْفَةٍ","إِذَا","تُمْنَىٰ"],"warsh":["مِن","نُّطْفَةٍ","اِذَا","تُمْن۪ىٰۖ"]},"sajda":false},{"n":47,"key":"53:47","text":{"hafs":"وَأَنَّ عَلَيْهِ ٱلنَّشْأَةَ ٱلْأُخْرَىٰ","warsh":"وَأَنَّ عَلَيْهِ اِ۬لنَّشْأَةَ اَ۬لُاخْر۪ىٰۖ"},"words":{"hafs":["وَأَنَّ","عَلَيْهِ","ٱلنَّشْأَةَ","ٱلْأُخْرَىٰ"],"warsh":["وَأَنَّ","عَلَيْهِ","اِ۬لنَّشْأَةَ","اَ۬لُاخْر۪ىٰۖ"]},"sajda":false},{"n":48,"key":"53:48","text":{"hafs":"وَأَنَّهُۥ هُوَ أَغْنَىٰ وَأَقْنَىٰ","warsh":"وَأَنَّهُۥ هُوَ أَغْن۪ىٰ وَأَقْن۪ىٰۖ"},"words":{"hafs":["وَأَنَّهُۥ","هُوَ","أَغْنَىٰ","وَأَقْنَىٰ"],"warsh":["وَأَنَّهُۥ","هُوَ","أَغْن۪ىٰ","وَأَقْن۪ىٰۖ"]},"sajda":false},{"n":49,"key":"53:49","text":{"hafs":"وَأَنَّهُۥ هُوَ رَبُّ ٱلشِّعْرَىٰ","warsh":"وَأَنَّهُۥ هُوَ رَبُّ اُ۬لشِّعْر۪ىٰۖ"},"words":{"hafs":["وَأَنَّهُۥ","هُوَ","رَبُّ","ٱلشِّعْرَىٰ"],"warsh":["وَأَنَّهُۥ","هُوَ","رَبُّ","اُ۬لشِّعْر۪ىٰۖ"]},"sajda":false},{"n":50,"key":"53:50","text":{"hafs":"وَأَنَّهُۥٓ أَهْلَكَ عَادًا ٱلْأُولَىٰ","warsh":"وَأَنَّهُۥٓ أَهْلَكَ عَاداٗ اَ۬لُّاول۪ىٰ"},"words":{"hafs":["وَأَنَّهُۥٓ","أَهْلَكَ","عَادًا","ٱلْأُولَىٰ"],"warsh":["وَأَنَّهُۥٓ","أَهْلَكَ","عَاداٗ","اَ۬لُّاول۪ىٰ"]},"sajda":false},{"n":51,"key":"53:51","text":{"hafs":"وَثَمُودَا۟ فَمَآ أَبْقَىٰ","warsh":"وَثَمُوداٗ فَمَآ أَبْق۪ىٰ"},"words":{"hafs":["وَثَمُودَا۟","فَمَآ","أَبْقَىٰ"],"warsh":["وَثَمُوداٗ","فَمَآ","أَبْق۪ىٰ"]},"sajda":false},{"n":52,"key":"53:52","text":{"hafs":"وَقَوْمَ نُوحٍ مِّن قَبْلُ ۖ إِنَّهُمْ كَانُوا۟ هُمْ أَظْلَمَ وَأَطْغَىٰ","warsh":"وَقَوْمَ نُوحٖ مِّن قَبْلُۖ إِنَّهُمْ كَانُواْ هُمُۥٓ أَظْلَمَ وَأَطْغ۪ىٰۖ"},"words":{"hafs":["وَقَوْمَ","نُوحٍ","مِّن","قَبْلُ","إِنَّهُمْ","كَانُوا۟","هُمْ","أَظْلَمَ","وَأَطْغَىٰ"],"warsh":["وَقَوْمَ","نُوحٖ","مِّن","قَبْلُۖ","إِنَّهُمْ","كَانُواْ","هُمُۥٓ","أَظْلَمَ","وَأَطْغ۪ىٰۖ"]},"sajda":false},{"n":53,"key":"53:53","text":{"hafs":"وَٱلْمُؤْتَفِكَةَ أَهْوَىٰ","warsh":"وَالْمُوتَفِكَةَ أَهْو۪ىٰۖ"},"words":{"hafs":["وَٱلْمُؤْتَفِكَةَ","أَهْوَىٰ"],"warsh":["وَالْمُوتَفِكَةَ","أَهْو۪ىٰۖ"]},"sajda":false},{"n":54,"key":"53:54","text":{"hafs":"فَغَشَّىٰهَا مَا غَشَّىٰ","warsh":"فَغَشّ۪يٰهَا مَا غَشّ۪ىٰۖ"},"words":{"hafs":["فَغَشَّىٰهَا","مَا","غَشَّىٰ"],"warsh":["فَغَشّ۪يٰهَا","مَا","غَشّ۪ىٰۖ"]},"sajda":false},{"n":55,"key":"53:55","text":{"hafs":"فَبِأَىِّ ءَالَآءِ رَبِّكَ تَتَمَارَىٰ","warsh":"فَبِأَيِّ ءَالَآءِ رَبِّكَ تَتَمَار۪ىٰۖ"},"words":{"hafs":["فَبِأَىِّ","ءَالَآءِ","رَبِّكَ","تَتَمَارَىٰ"],"warsh":["فَبِأَيِّ","ءَالَآءِ","رَبِّكَ","تَتَمَار۪ىٰۖ"]},"sajda":false},{"n":56,"key":"53:56","text":{"hafs":"هَٰذَا نَذِيرٌ مِّنَ ٱلنُّذُرِ ٱلْأُولَىٰٓ","warsh":"هَٰذَا نَذِيرٞ مِّنَ اَ۬لنُّذُرِ اِ۬لُاول۪ىٰٓۖ"},"words":{"hafs":["هَٰذَا","نَذِيرٌ","مِّنَ","ٱلنُّذُرِ","ٱلْأُولَىٰٓ"],"warsh":["هَٰذَا","نَذِيرٞ","مِّنَ","اَ۬لنُّذُرِ","اِ۬لُاول۪ىٰٓۖ"]},"sajda":false},{"n":57,"key":"53:57","text":{"hafs":"أَزِفَتِ ٱلْـَٔازِفَةُ","warsh":"أَزِفَتِ اِ۬لَازِفَةُۖ"},"words":{"hafs":["أَزِفَتِ","ٱلْـَٔازِفَةُ"],"warsh":["أَزِفَتِ","اِ۬لَازِفَةُۖ"]},"sajda":false},{"n":58,"key":"53:58","text":{"hafs":"لَيْسَ لَهَا مِن دُونِ ٱللَّهِ كَاشِفَةٌ","warsh":"لَيْسَ لَهَا مِن دُونِ اِ۬للَّهِ كَاشِفَةٌۖ"},"words":{"hafs":["لَيْسَ","لَهَا","مِن","دُونِ","ٱللَّهِ","كَاشِفَةٌ"],"warsh":["لَيْسَ","لَهَا","مِن","دُونِ","اِ۬للَّهِ","كَاشِفَةٌۖ"]},"sajda":false},{"n":59,"key":"53:59","text":{"hafs":"أَفَمِنْ هَٰذَا ٱلْحَدِيثِ تَعْجَبُونَ","warsh":"اَفَمِنْ هَٰذَا اَ۬لْحَدِيثِ تَعْجَبُونَ"},"words":{"hafs":["أَفَمِنْ","هَٰذَا","ٱلْحَدِيثِ","تَعْجَبُونَ"],"warsh":["اَفَمِنْ","هَٰذَا","اَ۬لْحَدِيثِ","تَعْجَبُونَ"]},"sajda":false},{"n":60,"key":"53:60","text":{"hafs":"وَتَضْحَكُونَ وَلَا تَبْكُونَ","warsh":"وَتَضْحَكُونَ وَلَا تَبْكُونَ"},"words":{"hafs":["وَتَضْحَكُونَ","وَلَا","تَبْكُونَ"],"warsh":["وَتَضْحَكُونَ","وَلَا","تَبْكُونَ"]},"sajda":false},{"n":61,"key":"53:61","text":{"hafs":"وَأَنتُمْ سَٰمِدُونَ","warsh":"وَأَنتُمْ سَٰمِدُونَۖ"},"words":{"hafs":["وَأَنتُمْ","سَٰمِدُونَ"],"warsh":["وَأَنتُمْ","سَٰمِدُونَۖ"]},"sajda":false},{"n":62,"key":"53:62","text":{"hafs":"فَٱسْجُدُوا۟ لِلَّهِ وَٱعْبُدُوا۟ ۩","warsh":"فَاسْجُدُواْ لِلهِ وَاعْبُدُواْۖ۩"},"words":{"hafs":["فَٱسْجُدُوا۟","لِلَّهِ","وَٱعْبُدُوا۟"],"warsh":["فَاسْجُدُواْ","لِلهِ","وَاعْبُدُواْۖ۩"]},"sajda":true}]}